image_cipher/__init__.py
image_cipher/cipher.py
imagecipher-0.1.0.dist-info/LICENSE
imagecipher-0.1.0.dist-info/METADATA
imagecipher-0.1.0.dist-info/WHEEL
imagecipher-0.1.0.dist-info/top_level.txt
imagecipher-0.1.0.dist-info/RECORD
