Metadata-Version: 2.1
Name: imagecipher
Version: 0.1.0
Summary: ImageCipherLib is a Python library designed for encrypting and decrypting images, offering a secure way to handle image data through customizable cipher algorithms.
Home-page: https://github.com/samadpls/ImageCipherLib
Author: samadpls
Author-email: abdulsamadsid1@gmail.com
License: UNKNOWN
Platform: UNKNOWN
Classifier: Programming Language :: Python :: 3
Classifier: License :: OSI Approved :: MIT License
Classifier: Operating System :: OS Independent
Requires-Python: >=3.6
Requires-Dist: Pillow >=10.4.0
Requires-Dist: cryptography >=42.0.8
Requires-Dist: wheel
